raycut/__init__.py
raycut-0.0.9.dist-info/METADATA
raycut-0.0.9.dist-info/WHEEL
raycut-0.0.9.dist-info/top_level.txt
raycut-0.0.9.dist-info/RECORD
