Metadata-Version: 2.1
Name: raycut
Version: 0.0.9
Summary: A convenience library for Ray that allows you to run a function on a remote
Home-page: http://github.com/d33tah/raycut
Author: Jacek "d33tah" Wielemborek
Author-email: d33tah@gmail.com
License: WTFPL
Requires-Dist: ray
Requires-Dist: boto3
Requires-Dist: pyyaml
